[{"Character":"","Skill":"Elite_0210","Item":"01-Elite_0210-220819_1827","Type":"Elite_0210","Event":"","montage":"01-Elite_0210-220819_1827","path":"","trackIndex":-1,"trackName":"Elite_0210","triggerTime":0.0,"attachName":"","bFollow":true},{"Character":"","Skill":"Track 2","Item":"01-Elite_0210-220819_1827","Type":"Track 2","Event":"","montage":"01-Elite_0210-220819_1827","path":"","trackIndex":-1,"trackName":"Track 2","triggerTime":4.5,"attachName":"","bFollow":true},{"Character":"","Skill":"Track 3","Item":"01-Elite_0210-220819_1827","Type":"Track 3","Event":"","montage":"01-Elite_0210-220819_1827","path":"","trackIndex":-1,"trackName":"Track 3","triggerTime":14.5,"attachName":"","bFollow":true}]